django_typer/__init__.py
django_typer/apps.py
django_typer/config.py
django_typer/patch.py
django_typer/py.typed
django_typer/types.py
django_typer/utils.py
django_typer/completers/__init__.py
django_typer/completers/apps.py
django_typer/completers/cmd.py
django_typer/completers/db.py
django_typer/completers/model.py
django_typer/completers/path.py
django_typer/completers/settings.py
django_typer/locale/af/LC_MESSAGES/django.po
django_typer/locale/ar/LC_MESSAGES/django.po
django_typer/locale/ar_DZ/LC_MESSAGES/django.po
django_typer/locale/az/LC_MESSAGES/django.po
django_typer/locale/be/LC_MESSAGES/django.po
django_typer/locale/bg/LC_MESSAGES/django.po
django_typer/locale/bn/LC_MESSAGES/django.po
django_typer/locale/br/LC_MESSAGES/django.po
django_typer/locale/bs/LC_MESSAGES/django.po
django_typer/locale/ca/LC_MESSAGES/django.po
django_typer/locale/ckb/LC_MESSAGES/django.po
django_typer/locale/cs/LC_MESSAGES/django.po
django_typer/locale/cy/LC_MESSAGES/django.po
django_typer/locale/da/LC_MESSAGES/django.po
django_typer/locale/de/LC_MESSAGES/django.po
django_typer/locale/el/LC_MESSAGES/django.po
django_typer/locale/en_AU/LC_MESSAGES/django.po
django_typer/locale/en_GB/LC_MESSAGES/django.po
django_typer/locale/eo/LC_MESSAGES/django.po
django_typer/locale/es/LC_MESSAGES/django.po
django_typer/locale/es_AR/LC_MESSAGES/django.po
django_typer/locale/es_CO/LC_MESSAGES/django.po
django_typer/locale/es_MX/LC_MESSAGES/django.po
django_typer/locale/es_VE/LC_MESSAGES/django.po
django_typer/locale/et/LC_MESSAGES/django.po
django_typer/locale/eu/LC_MESSAGES/django.po
django_typer/locale/fa/LC_MESSAGES/django.po
django_typer/locale/fi/LC_MESSAGES/django.po
django_typer/locale/fr/LC_MESSAGES/django.po
django_typer/locale/fy/LC_MESSAGES/django.po
django_typer/locale/ga/LC_MESSAGES/django.po
django_typer/locale/gd/LC_MESSAGES/django.po
django_typer/locale/gl/LC_MESSAGES/django.po
django_typer/locale/he/LC_MESSAGES/django.po
django_typer/locale/hi/LC_MESSAGES/django.po
django_typer-3.4.0.dist-info/METADATA
django_typer-3.4.0.dist-info/WHEEL
django_typer-3.4.0.dist-info/licenses/LICENSE
django_typer-3.4.0.dist-info/RECORD
