Metadata-Version: 2.4
Name: django-typer
Version: 3.4.0
Summary: Use Typer to define the CLI for your Django management commands.
Project-URL: Homepage, https://django-typer.readthedocs.io
Project-URL: Documentation, https://django-typer.readthedocs.io
Project-URL: Repository, https://github.com/django-commons/django-typer
Project-URL: Issues, https://github.com/django-commons/django-typer/issues
Project-URL: Changelog, https://django-typer.readthedocs.io/en/stable/changelog.html
Project-URL: Code_of_Conduct, https://github.com/django-commons/membership/blob/main/CODE_OF_CONDUCT.md
Author-email: Brian Kohan <bckohan@gmail.com>
License-Expression: MIT
License-File: LICENSE
Keywords: CLI,Typer,commands,django,management
Classifier: Development Status :: 5 - Production/Stable
Classifier: Environment :: Console
Classifier: Framework :: Django
Classifier: Framework :: Django :: 3.2
Classifier: Framework :: Django :: 4.0
Classifier: Framework :: Django :: 4.1
Classifier: Framework :: Django :: 4.2
Classifier: Framework :: Django :: 5.0
Classifier: Framework :: Django :: 5.1
Classifier: Framework :: Django :: 5.2
Classifier: Framework :: Django :: 6.0
Classifier: Intended Audience :: Developers
Classifier: License :: OSI Approved :: MIT License
Classifier: Natural Language :: English
Classifier: Operating System :: OS Independent
Classifier: Programming Language :: Python
Classifier: Programming Language :: Python :: 3.9
Classifier: Programming Language :: Python :: 3.10
Classifier: Programming Language :: Python :: 3.11
Classifier: Programming Language :: Python :: 3.12
Classifier: Programming Language :: Python :: 3.13
Classifier: Programming Language :: Python :: 3.14
Classifier: Topic :: Internet :: WWW/HTTP
Classifier: Topic :: Internet :: WWW/HTTP :: Site Management
Classifier: Topic :: Software Development :: Libraries
Classifier: Topic :: Software Development :: Libraries :: Python Modules
Requires-Python: <4.0,>=3.9
Requires-Dist: click<8.4,>=8.1.8
Requires-Dist: django<6.1,>=3.2
Requires-Dist: shellingham<2.0,>=1.5.4
Requires-Dist: typer-slim<0.21.0,>=0.20.0
Requires-Dist: typing-extensions>=3.7.4.3; python_version < '3.10'
Provides-Extra: rich
Requires-Dist: rich<15.0.0,>=10.11.0; extra == 'rich'
